python_snoo/__init__.py
python_snoo/commands.py
python_snoo/containers.py
python_snoo/exceptions.py
python_snoo/pubnub_async.py
python_snoo/snoo.py
python_snoo-1.0.0.dist-info/METADATA
python_snoo-1.0.0.dist-info/WHEEL
python_snoo-1.0.0.dist-info/RECORD
